{"user_id": "vinit@tribe.ai", "usages_date": "2021-08-09T00:00:00+00:00", "device": {"os": "Android", "brand": "OnePlus"}, "usages": [{"app_name": "slack", "minute_used": 156, "app_category": "communication"}, {"app_name": "gmail", "minute_used": 257, "app_category": "communication"}, {"app_name": "jira", "minute_used": 11, "app_category": "task_management"}, {"app_name": "google drive", "minute_used": 40, "app_category": "file_management"}, {"app_name": "mozila", "minute_used": 4, "app_category": "web_browser"}, {"app_name": "Resso", "minute_used": 5, "app_category": "entertainment_music"}]}